netatmoapi/__init__.py
netatmoapi/client.py
netatmoapi/station.py
netatmoapi-1.1.1.dist-info/LICENSE
netatmoapi-1.1.1.dist-info/METADATA
netatmoapi-1.1.1.dist-info/WHEEL
netatmoapi-1.1.1.dist-info/top_level.txt
netatmoapi-1.1.1.dist-info/RECORD
