Metadata-Version: 2.1
Name: netatmoapi
Version: 1.1.1
Summary: A simple Python wrapper of the Netatmo Connect API
Classifier: Programming Language :: Python :: 3
Classifier: License :: OSI Approved :: MIT License
Classifier: Operating System :: OS Independent
Requires-Python: >=3.7
License-File: LICENSE
Requires-Dist: requests
